example_package_muellerjo/__init__.py
example_package_muellerjo/example.py
example_package_muellerjo-0.0.2.dist-info/METADATA
example_package_muellerjo-0.0.2.dist-info/WHEEL
example_package_muellerjo-0.0.2.dist-info/licenses/LICENSE
example_package_muellerjo-0.0.2.dist-info/RECORD
