Metadata-Version: 2.1
Name: example_package_muellerjo
Version: 0.0.2
Summary: A small example package
Project-URL: Homepage, https://github.com/ebsone/dl_PyPI
Project-URL: Issues, https://github.com/ebsone/dl_PyPI/issues
Author-email: Jonas Müller <jo.mueller@sto.com>
License-File: LICENSE
Classifier: License :: OSI Approved :: MIT License
Classifier: Operating System :: OS Independent
Classifier: Programming Language :: Python :: 3
Requires-Python: >=3.8
